MrBayeStruConverter/__init__.py
MrBayeStruConverter/converter.py
mrbayes-ss-converter/__init__.py
mrbayes-ss-converter/converter.py
MrBayeStruConverter-0.0.2.dist-info/LICENSE
MrBayeStruConverter-0.0.2.dist-info/METADATA
MrBayeStruConverter-0.0.2.dist-info/WHEEL
MrBayeStruConverter-0.0.2.dist-info/top_level.txt
MrBayeStruConverter-0.0.2.dist-info/RECORD
