Metadata-Version: 2.1
Name: MrBayeStruConverter
Version: 0.0.2
Summary: UNKNOWN
Home-page: https://github.com/sgelias/mrbayes-ss-converter.git
Author: Samuel Galvão Elias
Author-email: sgelias@outlook.com
License: UNKNOWN
Keywords: MrBayes,Phylogeny,Ribosome
Platform: UNKNOWN
Classifier: Programming Language :: Python :: 3
Classifier: License :: OSI Approved :: MIT License
Classifier: Operating System :: OS Independent
Requires-Python: >=3.0
